forecast_eval/__init__.py
forecast_eval/baselines.py
forecast_eval/evaluator.py
forecast_eval/metrics.py
forecast_eval/reporting_html.py
forecast_eval/reporting_text.py
forecast_eval/stats_tests.py
forecasteval-0.2.4.dist-info/licenses/LICENSE
forecasteval-0.2.4.dist-info/METADATA
forecasteval-0.2.4.dist-info/WHEEL
forecasteval-0.2.4.dist-info/top_level.txt
forecasteval-0.2.4.dist-info/RECORD
