Metadata-Version: 2.4
Name: forecastEval
Version: 0.2.4
Summary: A lightweight Python framework for rigorous and statistically grounded forecast evaluation, with baseline comparison, horizon-stratified analysis, and Diebold–Mariano testing.
Author-email: Bruna Azevedo <bcado@isep.ipp.pt>, Luís Gomes <log@isep.ipp.pt>, Zita Vale <zav@isep.ipp.pt>
License-Expression: GPL-3.0-only
Project-URL: Homepage, https://github.com/gecad-group/BCADO_forecast-eval
Project-URL: Issues, https://github.com/gecad-group/BCADO_forecast-eval/issues
Classifier: Programming Language :: Python :: 3
Classifier: Operating System :: OS Independent
Requires-Python: >=3.9
License-File: LICENSE
Dynamic: license-file
